{
    "name":                  "weekly",
    "gui_name":              "Weekly",
    "description":           "Hint distribution for the weekly races: 5 Always, 6 Goal, 4 Barren at ToT, 5 Sometimes, 2 Dual, 30/40/50 hinted at Skull House.",
    "add_locations":         [
        { "location": "Sheik in Kakariko", "types": ["always"] },
        { "location": "Deku Theater Skull Mask", "types": ["always"] }
    ],
    "remove_locations":      [
        { "location": "Song from Royal Familys Tomb", "types": ["sometimes"] },
        { "location": "Sheik in Forest", "types": ["sometimes"] },
        { "location": "Sheik at Temple", "types": ["sometimes"] },
        { "location": "Sheik in Crater", "types": ["sometimes"] },
        { "location": "Sheik in Ice Cavern", "types": ["sometimes"] },
        { "location": "Sheik at Colossus", "types": ["sometimes"] },
        { "location": "GF HBA 1500 Points", "types": ["sometimes"] },
        { "location": "GC Maze Left Chest", "types": ["sometimes"] },
        { "location": "GV Chest", "types": ["sometimes"] },
        { "location": "HC Great Fairy Reward", "types": ["sometimes"] },
        { "location": "OGC Great Fairy Reward", "types": ["sometimes"] },
        { "location": "Gerudo Training Ground Maze Path Final Chest", "types": ["sometimes"] },
        { "location": "Ice Cavern Iron Boots Chest", "types": ["sometimes"] },
        { "location": "Graveyard Dampe Race Rewards", "types": ["dual"] },
        { "location": "Graveyard Royal Family Tomb Contents", "types": ["dual"] },
        { "location": "Fire Temple Lower Loop", "types": ["dual"] },
        { "location": "Water Temple River Loop Chests", "types": ["dual"] },
        { "location": "Spirit Temple Colossus Hands", "types": ["dual"] },
        { "location": "Spirit Temple Child Lower", "types": ["dual"] },
        { "location": "Spirit Temple Adult Lower", "types": ["dual"] },
        { "location": "Shadow Temple Invisible Blades Chests", "types": ["dual"] },
        { "location": "Shadow Temple Spike Walls Room", "types": ["dual"] }
    ],
    "add_items":             [],
    "remove_items":          [
        { "item": "Zeldas Lullaby", "types": ["goal"] }
    ],
    "dungeons_barren_limit": 1,
    "named_items_required":  true,
    "vague_named_items":     false,
    "use_default_goals":     true,
    "distribution":          {
        "trial":           {"order": 1, "weight": 0.0, "fixed": 0, "copies": 2},
        "entrance_always": {"order": 2, "weight": 0.0, "fixed": 0, "copies": 2},
        "always":          {"order": 3, "weight": 0.0, "fixed": 0, "copies": 2, "remove_stones": [
            "ToT (Left)",
            "ToT (Left-Center)",
            "ToT (Right-Center)",
            "ToT (Right)"
        ]},
        "goal":            {"order": 4, "weight": 0.0, "fixed": 6, "copies": 2, "remove_stones": [
            "ToT (Left)",
            "ToT (Left-Center)",
            "ToT (Right-Center)",
            "ToT (Right)"
        ]},
        "barren":          {"order": 5, "weight": 0.0, "fixed": 4, "copies": 1, "priority_stones": [
            "ToT (Left)",
            "ToT (Left-Center)",
            "ToT (Right-Center)",
            "ToT (Right)"
        ]},
        "entrance":        {"order": 6, "weight": 0.0, "fixed": 0, "copies": 2},
        "dual":            {"order": 7, "weight": 0.0, "fixed": 2, "copies": 2},
        "sometimes":       {"order": 8, "weight": 1.0, "fixed": 0, "copies": 2},
        "random":          {"order": 0, "weight": 0.0, "fixed": 0, "copies": 2},
        "item":            {"order": 0, "weight": 0.0, "fixed": 0, "copies": 2},
        "song":            {"order": 0, "weight": 0.0, "fixed": 0, "copies": 2},
        "overworld":       {"order": 0, "weight": 0.0, "fixed": 0, "copies": 2},
        "dungeon":         {"order": 0, "weight": 0.0, "fixed": 0, "copies": 2},
        "junk":            {"order": 0, "weight": 0.0, "fixed": 0, "copies": 2},
        "named-item":      {"order": 0, "weight": 0.0, "fixed": 0, "copies": 2},
        "woth":            {"order": 0, "weight": 0.0, "fixed": 0, "copies": 2},
        "dual_always":     {"order": 0, "weight": 0.0, "fixed": 0, "copies": 2},
        "important_check": {"order": 0, "weight": 0.0, "fixed": 0, "copies": 2}
    }
}
